dynamic_subdomains/__init__.py
dynamic_subdomains/app_settings.py
dynamic_subdomains/apps.py
dynamic_subdomains/middleware.py
dynamic_subdomains/reverse.py
dynamic_subdomains/subdomains.py
dynamic_subdomains/utils.py
django_dynamic_subdomains_simple-2.0.1.dist-info/LICENSE
django_dynamic_subdomains_simple-2.0.1.dist-info/METADATA
django_dynamic_subdomains_simple-2.0.1.dist-info/WHEEL
django_dynamic_subdomains_simple-2.0.1.dist-info/top_level.txt
django_dynamic_subdomains_simple-2.0.1.dist-info/RECORD
