Metadata-Version: 2.1
Name: django-dynamic-subdomains-simple
Version: 2.0.1
Summary: Dynamic and static subdomain support for Django.
Home-page: UNKNOWN
Author: Chris Adkins
Author-email: c23gooey@gmail.com
License: MIT
Platform: UNKNOWN
Requires-Dist: Django (>=2.2)
